nr/__init__.py
nr/pylang/__init__.py
nr/pylang/ast/__init__.py
nr/pylang/ast/dynamic_eval.py
nr.pylang.ast-0.0.5.dist-info/LICENSE.txt
nr.pylang.ast-0.0.5.dist-info/METADATA
nr.pylang.ast-0.0.5.dist-info/WHEEL
nr.pylang.ast-0.0.5.dist-info/top_level.txt
nr.pylang.ast-0.0.5.dist-info/zip-safe
nr.pylang.ast-0.0.5.dist-info/RECORD
