Metadata-Version: 2.1
Name: nr.pylang.ast
Version: 0.0.5
Summary: Package description here.
Home-page: https://git.niklasrosenstein.com/NiklasRosenstein/nr
Author: Niklas Rosenstein
Author-email: rosensteinniklas@gmail.com
License: MIT
Platform: UNKNOWN
Requires-Python: >=3.4.0,<4.0.0
Requires-Dist: nr.collections (<1.0.0,>=0.0.1)
